azul_marl_env/__init__.py
azul_marl_env/azul_env.py
azul_marl_env/simulator.py
azul_marl_env-1.0.6.dist-info/licenses/LICENSE
azul_marl_env-1.0.6.dist-info/METADATA
azul_marl_env-1.0.6.dist-info/WHEEL
azul_marl_env-1.0.6.dist-info/top_level.txt
azul_marl_env-1.0.6.dist-info/RECORD
