Metadata-Version: 2.4
Name: azul_marl_env
Version: 1.0.6
Summary: A library to enable AI agent training on board game
Author-email: Evaldas Visockas <developersediary@gmail.com>
License: GPL-3.0-or-later
Project-URL: Repository, https://github.com/AzulImplementation/AzulMARL
Requires-Python: >=3.12
License-File: LICENSE
Requires-Dist: azul-game-engine>=1.0.2
Requires-Dist: pettingzoo>=1.24.3
Requires-Dist: gymnasium>=1.0.0
Requires-Dist: numpy>=1.21.0
Requires-Dist: matplotlib>=3.10.1
Provides-Extra: test
Requires-Dist: pytest>=7.0.0; extra == "test"
Requires-Dist: numpy>=1.21.0; extra == "test"
Dynamic: license-file
